captcha_recognizer/__init__.py
captcha_recognizer/cli.py
captcha_recognizer/config/charsets.txt
captcha_recognizer/config/model_config.json
captcha_recognizer/models/__init__.py
captcha_recognizer/models/litecnn.py
captcha_recognizer/models/litecnn_.py
captcha_recognizer/output/custom_captcha_model/model.pth
captcha_recognizer/utils/__init__.py
captcha_recognizer/utils/recognizer.py
icbc_captcha_recognizer-0.1.1.dist-info/METADATA
icbc_captcha_recognizer-0.1.1.dist-info/WHEEL
icbc_captcha_recognizer-0.1.1.dist-info/entry_points.txt
icbc_captcha_recognizer-0.1.1.dist-info/top_level.txt
icbc_captcha_recognizer-0.1.1.dist-info/RECORD
